test/optFIR.v
`timescale 1ns / 1ps
/*
============ FIR filter ====================
*/
module optFIR_Filter
  #(parameter N  = 16)
  (
    input         clk,
    input         rst,
    input         en,
    input [N-1:0] X,
    input [N-1:0] b0,
    input [N-1:0] b1,
    output [N-1:0]   Y);
  
  reg [N-1:0] X1, X2, X3, X4;
  reg [2:0] phase;
  wire muxsel;
  reg cycle_valid;
  
  wire [N-1:0] coeff;
  reg [N-1:0] samplevalue;
  reg [N-1:0] Yt;
  reg [N-1:0] result; 

  //reg [N-1:0] Yt;
  
 // assign Y = Yt;
 // assign Yt = (X*b0 + X1*b1 + X2*b2 + X3*b3) >> SHIFT;

  assign muxsel = ((phase == 2'b00) || (phase == 2'b11)) ? 0 : 1;
  assign coeff  =  (!muxsel)  ? b0 : b1;
  assign Y = Yt; 
  
  always@(phase or X1 or X2 or X3 or X4) begin

	if (phase == 2'b00)
         samplevalue <= X1; 
   	else if (phase == 2'b01)
         samplevalue <= X2;
   	else if (phase == 2'b10)
         samplevalue <= X3;
   	else if (phase == 2'b11)
			samplevalue <= X4;
    else
         samplevalue <= 0;
  end

/* shift the samples and the result each sample period WE_PCM */  
  always@(posedge clk) begin
    if(rst ==1'b1) 
    begin
      X1 <= 0;
      X2 <= 0;
      X3 <= 0;
      X3 <= 0;
    end
    else if(en == 1) 
    begin 
      X1 <= X;
      X2 <= X1;
      X3 <= X2;
      X4 <= X3;
    end
   if(phase == 3'b100)
       Yt <= result;
  end

  always@(posedge clk) begin
    if(rst ==1'b1) 
    begin
		result <= 0;
    end
    else begin
    if(cycle_valid)  
		result <= result + ((samplevalue*coeff) >> 4);
    if(phase == 3'b101)
        result <= 0;
    end
  end

/*phase of the computation*/
   always@(posedge clk) begin
    if(rst ==1'b1) 
    begin
		phase <= 0;
    end
    else if(cycle_valid)
       	phase <= phase + 1;

end

/*phase of the computation*/
   always@(posedge clk) begin
    if(rst ==1'b1) 
		cycle_valid <= 0;
    else if(en == 1'b1) 
         cycle_valid <= 1;
    else if(phase == 3'b011) begin
         cycle_valid <= 0;
         end
  end

endmodule

test/testbench.v
/*
Testbench for XST sytnthesis user guide examples
*/
//-----------------------------------------------------------
module Filter_behavioral_tb;
  
  parameter N = 16;
  reg clk, rst, en;
  reg [N-1:0] X, b0, b1;
  wire [N-1:0] Y;

  
  
/* Module instantiation */  
 optFIR_Filter fir(clk, rst, en, X, b0, b1, Y);
  

/* clock signal generation*/  
initial begin
  clk=0;
  forever #5 clk = ~clk;  
end 
  
initial begin
       X  = 1;
       b0 = 16;
       b1 = 32;
       en = 0;
       rst = 1'b0;
  #10  rst = 1'b1;
  #10  rst = 1'b0;
        X <= 2 ;
  #15  en = 1'b1;
  #10  en = 1'b0;  
        X <= 3 ;
  #100  en = 1'b1;
  #10  en = 1'b0;  
        X <= 4 ;
  #100  en = 1'b1;
  #10  en = 1'b0;  
        X <= 5 ; 
  #100  en = 1'b1;
  #10  en = 1'b0; 
        X <= 6 ; 
  #100  en = 1'b1;
  #10  en = 1'b0;  
  #100 $finish;
end
/* Monitor and dump */  
initial begin
 // $monitor ("%t | CLK = %d| D = %d| Q = %d", $time, clk, set, Q2);
    $dumpfile("dump.vcd");
    $dumpvars();
end
endmodule

test/dump.vcd
$date
	Sun Oct 10 14:02:25 2021
$end
$version
	Icarus Verilog
$end
$timescale
	1ps
$end
$scope module Filter_behavioral_tb $end
$var wire 16 ! Y [15:0] $end
$var reg 16 " X [15:0] $end
$var reg 16 # b0 [15:0] $end
$var reg 16 $ b1 [15:0] $end
$var reg 1 % clk $end
$var reg 1 & en $end
$var reg 1 ' rst $end
$scope module fir $end
$var wire 16 ( X [15:0] $end
$var wire 16 ) Y [15:0] $end
$var wire 16 * b0 [15:0] $end
$var wire 16 + b1 [15:0] $end
$var wire 1 % clk $end
$var wire 1 & en $end
$var wire 1 ' rst $end
$var wire 1 , muxsel $end
$var wire 16 - coeff [15:0] $end
$var reg 16 . X1 [15:0] $end
$var reg 16 / X2 [15:0] $end
$var reg 16 0 X3 [15:0] $end
$var reg 16 1 X4 [15:0] $end
$var reg 16 2 Yt [15:0] $end
$var reg 1 3 cycle_valid $end
$var reg 3 4 phase [2:0] $end
$var reg 16 5 result [15:0] $end
$var reg 16 6 samplevalue [15:0] $end
$upscope $end
$upscope $end
$enddefinitions $end
#0
$dumpvars
bx 6
bx 5
bx 4
x3
bx 2
bx 1
bx 0
bx /
bx .
b0xx0000 -
x,
b100000 +
b10000 *
bx )
b1 (
0'
0&
0%
b100000 $
b10000 #
b1 "
bx !
$end
#5000
1%
#10000
0%
1'
#15000
b0 6
b10000 -
0,
03
b0 4
b0 5
b0 0
b0 /
b0 .
1%
#20000
b10 "
b10 (
0%
0'
#25000
1%
#30000
0%
#35000
b10 6
13
b0 1
b10 .
1%
1&
#40000
0%
#45000
b0 6
b100000 -
1,
b10 5
b1 4
b11 "
b11 (
1%
0&
#50000
0%
#55000
b10 4
1%
#60000
0%
#65000
b10000 -
0,
b11 4
1%
#70000
0%
#75000
b100000 -
1,
03
b100 4
1%
#80000
0%
#85000
b10 !
b10 )
b10 2
1%
#90000
0%
#95000
1%
#100000
0%
#105000
1%
#110000
0%
#115000
1%
#120000
0%
#125000
1%
#130000
0%
#135000
1%
#140000
0%
#145000
b10 /
b11 .
13
1%
1&
#150000
0%
#155000
b101 4
b100 "
b100 (
1%
0&
#160000
0%
#165000
b0 5
b110 4
1%
#170000
0%
#175000
b111 4
1%
#180000
0%
#185000
b11 6
b10000 -
0,
b0 4
1%
#190000
0%
#195000
b10 6
b100000 -
1,
b1 4
b11 5
1%
#200000
0%
#205000
b0 6
b111 5
b10 4
1%
#210000
0%
#215000
b10000 -
0,
b11 4
1%
#220000
0%
#225000
b100000 -
1,
b100 4
03
1%
#230000
0%
#235000
b111 !
b111 )
b111 2
1%
#240000
0%
#245000
1%
#250000
0%
#255000
13
b10 0
b11 /
b100 .
1%
1&
#260000
0%
#265000
b101 4
b101 "
b101 (
1%
0&
#270000
0%
#275000
b110 4
b0 5
1%
#280000
0%
#285000
b111 4
1%
#290000
0%
#295000
b100 6
b10000 -
0,
b0 4
1%
#300000
0%
#305000
b11 6
b100000 -
1,
b100 5
b1 4
1%
#310000
0%
#315000
b10 6
b10 4
b1010 5
1%
#320000
0%
#325000
b0 6
b10000 -
0,
b1110 5
b11 4
1%
#330000
0%
#335000
b100000 -
1,
03
b100 4
1%
#340000
0%
#345000
b1110 !
b1110 )
b1110 2
1%
#350000
0%
#355000
1%
#360000
0%
#365000
b10 1
b11 0
b100 /
b101 .
13
1%
1&
#370000
0%
#375000
b101 4
b110 "
b110 (
1%
0&
#380000
0%
#385000
b0 5
b110 4
1%
#390000
0%
#395000
b111 4
1%
#400000
0%
#405000
b101 6
b10000 -
0,
b0 4
1%
#410000
0%
#415000
b100 6
b100000 -
1,
b1 4
b101 5
1%
#420000
0%
#425000
b11 6
b1101 5
b10 4
1%
#430000
0%
#435000
b10 6
b10000 -
0,
b11 4
b10011 5
1%
#440000
0%
#445000
b0 6
b100000 -
1,
b10101 5
b100 4
03
1%
#450000
0%
#455000
b10101 !
b10101 )
b10101 2
1%
#460000
0%
#465000
1%
#470000
0%
#475000
13
b11 1
b100 0
b101 /
b110 .
1%
1&
#480000
0%
#485000
b101 4
1%
0&
#490000
0%
#495000
b110 4
b0 5
1%
#500000
0%
#505000
b111 4
1%
#510000
0%
#515000
b110 6
b10000 -
0,
b0 4
1%
#520000
0%
#525000
b101 6
b100000 -
1,
b110 5
b1 4
1%
#530000
0%
#535000
b100 6
b10 4
b10000 5
1%
#540000
0%
#545000
b11 6
b10000 -
0,
b11000 5
b11 4
1%
#550000
0%
#555000
b0 6
b100000 -
1,
03
b100 4
b11011 5
1%
#560000
0%
#565000
b11011 !
b11011 )
b11011 2
1%
