src/IIR_Filter.v
/*
IIR filter for MPW-2
*/
module IIR_Filter
  #(
    parameter N  = 16)
  (
    input wire clk,
    input wire rst,
    input wire en,
    input wire [N-1:0] X,
    input wire [N-1:0] a0,
    input wire [N-1:0] a1,
    input wire [N-1:0] a2,
    input wire [N-1:0] b1,
    input wire [N-1:0] b2,
    output  [N-1:0] Y);
  
  reg [N-1:0] X1, X2, X3;
  reg [N-1:0] Y1, Y2;
  reg [N-1:0] Yt;
  
  reg [2:0] phase;
  reg cycle_valid;
  
  reg [N-1:0] coeff;
  reg [N-1:0] samplevalue;
  reg [N-1:0] result; 

  assign Y = Yt; 
  
  always@(phase or X1 or X2 or X3 or Y1 or Y2 ) begin

	if (phase == 3'b000) begin
         samplevalue <= X1; 
         coeff <=  a0;
    end 
	else if (phase == 3'b001) begin
         samplevalue <= X2; 
         coeff <=  a1;
    end 
	else if (phase == 3'b010) begin
         samplevalue <= X3; 
         coeff <=  a2;
    end 
	else if (phase == 3'b011) begin
         samplevalue <= Y1; 
         coeff <=  b1;
    end 
	else if (phase == 3'b100) begin
         samplevalue <= Y2; 
         coeff <=  b2;
    end 
    else
         samplevalue <= 0;
  end


  
  always@(posedge clk) begin
    if(rst ==1'b1) 
    begin
      Y1 <= 0;
      Y2 <= 0;
      X1 <= 0;
      X2 <= 0;
      X3 <= 0;
      Yt <= 0;
    end
    else if(en == 1'b1) 
    begin 
      Y1 <= Yt;
      Y2 <= Y1;
      X1 <= X;
      X2 <= X1;
      X3 <= X2;
    end
   if(phase == 3'b110)
       Yt <= result;
  end

  always@(posedge clk) begin
    if(rst ==1'b1) 
    begin
		result <= 0;
    end
    else begin
    if(cycle_valid)  
		result <= result + ((samplevalue*coeff) >> 4);
    if(phase == 3'b111)
        result <= 0;
    end
  end

/*phase of the computation*/
   always@(posedge clk) begin
    if(rst ==1'b1) 
    begin
		phase <= 0;
    end
    else if(cycle_valid)
       	phase <= phase + 1;
    end

/*phase of the computation*/
   always@(posedge clk) begin
    if(rst ==1'b1) 
		cycle_valid <= 0;
    else if(en == 1'b1) 
         cycle_valid <= 1;
    else if(phase == 3'b101) begin
         cycle_valid <= 0;
         end
   end

  
endmodule

test/optFIR.v
`timescale 1ns / 1ps
/*
============ FIR filter ====================
*/
module optFIR_Filter
  #(parameter N  = 16)
  (
    input         clk,
    input         rst,
    input         en,
    input [N-1:0] X,
    input [N-1:0] b0,
    input [N-1:0] b1,
    output [N-1:0]   Y);
  
  reg [N-1:0] X1, X2, X3, X4;
  reg [2:0] phase;
  wire muxsel;
  reg cycle_valid;
  
  wire [N-1:0] coeff;
  reg [N-1:0] samplevalue;
  reg [N-1:0] Yt;
  reg [N-1:0] result; 



  assign muxsel = ((phase == 2'b00) || (phase == 2'b11)) ? 0 : 1;
  assign coeff  =  (!muxsel)  ? b0 : b1;
  assign Y = Yt; 
  
  always@(phase or X1 or X2 or X3 or X4) begin

	if (phase == 2'b00)
         samplevalue <= X1; 
   	else if (phase == 2'b01)
         samplevalue <= X2;
   	else if (phase == 2'b10)
         samplevalue <= X3;
   	else if (phase == 2'b11)
			samplevalue <= X4;
    else
         samplevalue <= 0;
  end

/* shift the samples and the result each sample period WE_PCM */  
  always@(posedge clk) begin
    if(rst ==1'b1) 
    begin
      X1 <= 0;
      X2 <= 0;
      X3 <= 0;
      X3 <= 0;
    end
    else if(en == 1) 
    begin 
      X1 <= X;
      X2 <= X1;
      X3 <= X2;
      X4 <= X3;
    end
   if(phase == 3'b100)
       Yt <= result;
  end

  always@(posedge clk) begin
    if(rst ==1'b1) 
    begin
		result <= 0;
    end
    else begin
    if(cycle_valid)  
		result <= result + ((samplevalue*coeff) >> 4);
    if(phase == 3'b101)
        result <= 0;
    end
  end

/*phase of the computation*/
   always@(posedge clk) begin
    if(rst ==1'b1) 
    begin
		phase <= 0;
    end
    else if(cycle_valid)
       	phase <= phase + 1;
    end

/*phase of the computation*/
   always@(posedge clk) begin
    if(rst ==1'b1) 
		cycle_valid <= 0;
    else if(en == 1'b1) 
         cycle_valid <= 1;
    else if(phase == 3'b011) begin
         cycle_valid <= 0;
         end
  end

endmodule

test/testbench_filters.v
/*
Testbench for XST sytnthesis user guide examples
*/
//-----------------------------------------------------------
module Filter_behavioral_tb;
  
  parameter N = 16;
  reg clk, rst, en;
  reg signed [N-1:0] X, b0, b1, a0, a1, a2;
  wire [N-1:0] Y, Yir;

  
  
/* Module instantiation */  
 optFIR_Filter fir(clk, rst, en, X, b0, b1, Y);
 IIR_Filter   iir(clk, rst, en, X, a0,a1,a2,b0,b1, Yir);
  

/* clock signal generation*/  
initial begin
  clk=0;
  forever #5 clk = ~clk;  
end 
  
initial begin
       X  =0;
       b0 = -2676;
       b1 = 18952;
       a0 = 16;
       a1 = 32;
       a2 = 64;
       en = 0;
       rst = 1'b0;
  #10  rst = 1'b1;
  #10  rst = 1'b0;
        X <= 0 ;
  #15  en = 1'b1;
  #10  en = 1'b0;  
        X <= 0 ;
  #100  en = 1'b1;
  #10  en = 1'b0;  
        X <=  32767 ;
  #100  en = 1'b1;
  #10  en = 1'b0;  
        X <= 0 ; 
  #100  en = 1'b1;
  #10  en = 1'b0; 
        X <= 0 ; 
  #100  en = 1'b1;
  #10  en = 1'b0; 
  #100  en = 1'b1;
  #10  en = 1'b0;  
  #100  en = 1'b1;
  #10  en = 1'b0;  
  #100  en = 1'b1;
  #10  en = 1'b0;  
  #100  en = 1'b1;
  #10  en = 1'b0;   
  #100 $finish;
end
/* Monitor and dump */  
initial begin
 // $monitor ("%t | CLK = %d| D = %d| Q = %d", $time, clk, set, Q2);
    $dumpfile("dump.vcd");
    $dumpvars();
end
endmodule

test/dump.vcd
$date
	Sun Oct 10 15:48:42 2021
$end
$version
	Icarus Verilog
$end
$timescale
	1ps
$end
$scope module Filter_behavioral_tb $end
$var wire 16 ! Yir [15:0] $end
$var wire 16 " Y [15:0] $end
$var reg 16 # X [15:0] $end
$var reg 16 $ a0 [15:0] $end
$var reg 16 % a1 [15:0] $end
$var reg 16 & a2 [15:0] $end
$var reg 16 ' b0 [15:0] $end
$var reg 16 ( b1 [15:0] $end
$var reg 1 ) clk $end
$var reg 1 * en $end
$var reg 1 + rst $end
$scope module fir $end
$var wire 16 , X [15:0] $end
$var wire 16 - Y [15:0] $end
$var wire 16 . b0 [15:0] $end
$var wire 16 / b1 [15:0] $end
$var wire 1 ) clk $end
$var wire 1 * en $end
$var wire 1 + rst $end
$var wire 1 0 muxsel $end
$var wire 16 1 coeff [15:0] $end
$var reg 16 2 X1 [15:0] $end
$var reg 16 3 X2 [15:0] $end
$var reg 16 4 X3 [15:0] $end
$var reg 16 5 X4 [15:0] $end
$var reg 16 6 Yt [15:0] $end
$var reg 1 7 cycle_valid $end
$var reg 3 8 phase [2:0] $end
$var reg 16 9 result [15:0] $end
$var reg 16 : samplevalue [15:0] $end
$upscope $end
$scope module iir $end
$var wire 16 ; X [15:0] $end
$var wire 16 < Y [15:0] $end
$var wire 16 = a0 [15:0] $end
$var wire 16 > a1 [15:0] $end
$var wire 16 ? a2 [15:0] $end
$var wire 16 @ b1 [15:0] $end
$var wire 16 A b2 [15:0] $end
$var wire 1 ) clk $end
$var wire 1 * en $end
$var wire 1 + rst $end
$var reg 16 B X1 [15:0] $end
$var reg 16 C X2 [15:0] $end
$var reg 16 D X3 [15:0] $end
$var reg 16 E Y1 [15:0] $end
$var reg 16 F Y2 [15:0] $end
$var reg 16 G Yt [15:0] $end
$var reg 16 H coeff [15:0] $end
$var reg 1 I cycle_valid $end
$var reg 3 J phase [2:0] $end
$var reg 16 K result [15:0] $end
$var reg 16 L samplevalue [15:0] $end
$upscope $end
$upscope $end
$enddefinitions $end
#0
$dumpvars
bx L
bx K
bx J
xI
bx H
bx G
bx F
bx E
bx D
bx C
bx B
b100000 A
b10000 @
b1000000 ?
b100000 >
b10000 =
bx <
b1 ;
bx :
bx 9
bx 8
x7
bx 6
bx 5
bx 4
bx 3
bx 2
b0xx0000 1
x0
b100000 /
b10000 .
bx -
b1 ,
0+
0*
0)
b100000 (
b10000 '
b1000000 &
b100000 %
b10000 $
b1 #
bx "
bx !
$end
#5000000000000
1)
#10000000000000
0)
1+
#15000000000000
b10000 H
b0 L
b0 :
b10000 1
00
0I
b0 J
b0 K
b0 !
b0 <
b0 G
b0 D
b0 C
b0 B
b0 F
b0 E
07
b0 8
b0 9
b0 4
b0 3
b0 2
1)
#20000000000000
b10 #
b10 ,
b10 ;
0)
0+
#25000000000000
1)
#30000000000000
0)
#35000000000000
b10 L
b10 :
1I
b10 B
17
b0 5
b10 2
1)
1*
#40000000000000
0)
#45000000000000
b0 :
b100000 H
b0 L
b100000 1
10
b10 9
b1 8
b10 K
b1 J
b11 #
b11 ,
b11 ;
1)
0*
#50000000000000
0)
#55000000000000
b1000000 H
b10 J
b10 8
1)
#60000000000000
0)
#65000000000000
b10000 H
b10000 1
00
b11 8
b11 J
1)
#70000000000000
0)
#75000000000000
b100000 H
b100000 1
10
b100 J
07
b100 8
1)
#80000000000000
0)
#85000000000000
b10 "
b10 -
b10 6
b101 J
1)
#90000000000000
0)
#95000000000000
0I
b110 J
1)
#100000000000000
0)
#105000000000000
b10 !
b10 <
b10 G
1)
#110000000000000
0)
#115000000000000
1)
#120000000000000
0)
#125000000000000
1)
#130000000000000
0)
#135000000000000
1)
#140000000000000
0)
#145000000000000
b10 3
b11 2
17
b10 C
b11 B
b10 E
1I
1)
1*
#150000000000000
0)
#155000000000000
b111 J
b101 8
b100 #
b100 ,
b100 ;
1)
0*
#160000000000000
0)
#165000000000000
b10000 H
b11 L
b0 9
b110 8
b0 K
b0 J
1)
#170000000000000
0)
#175000000000000
b100000 H
b10 L
b1 J
b11 K
b111 8
1)
#180000000000000
0)
#185000000000000
b11 :
b1000000 H
b0 L
b10000 1
00
b0 8
b111 K
b10 J
1)
#190000000000000
0)
#195000000000000
b10000 H
b10 L
b10 :
b100000 1
10
b11 J
b1 8
b11 9
1)
#200000000000000
0)
#205000000000000
b0 :
b100000 H
b0 L
b111 9
b10 8
b1001 K
b100 J
1)
#210000000000000
0)
#215000000000000
b10000 1
00
b101 J
b11 8
1)
#220000000000000
0)
#225000000000000
b100000 1
10
b100 8
07
b110 J
0I
1)
#230000000000000
0)
#235000000000000
b1001 !
b1001 <
b1001 G
b111 "
b111 -
b111 6
1)
#240000000000000
0)
#245000000000000
1)
#250000000000000
0)
#255000000000000
1I
b10 D
b11 C
b100 B
b10 F
b1001 E
17
b10 4
b11 3
b100 2
1)
1*
#260000000000000
0)
#265000000000000
b101 8
b111 J
b101 #
b101 ,
b101 ;
1)
0*
#270000000000000
0)
#275000000000000
b10000 H
b100 L
b0 J
b0 K
b110 8
b0 9
1)
#280000000000000
0)
#285000000000000
b100000 H
b11 L
b111 8
b100 K
b1 J
1)
#290000000000000
0)
#295000000000000
b1000000 H
b10 L
b100 :
b10000 1
00
b10 J
b1010 K
b0 8
1)
#300000000000000
0)
#305000000000000
b11 :
b10000 H
b1001 L
b100000 1
10
b100 9
b1 8
b10010 K
b11 J
1)
#310000000000000
0)
#315000000000000
b100000 H
b10 L
b10 :
b100 J
b11011 K
b10 8
b1010 9
1)
#320000000000000
0)
#325000000000000
b0 :
b0 L
b10000 1
00
b1110 9
b11 8
b11111 K
b101 J
1)
#330000000000000
0)
#335000000000000
b100000 1
10
0I
b110 J
07
b100 8
1)
#340000000000000
0)
#345000000000000
b1110 "
b1110 -
b1110 6
b11111 !
b11111 <
b11111 G
1)
#350000000000000
0)
#355000000000000
1)
#360000000000000
0)
#365000000000000
b10 5
b11 4
b100 3
b101 2
17
b11 D
b100 C
b101 B
b1001 F
b11111 E
1I
1)
1*
#370000000000000
0)
#375000000000000
b111 J
b101 8
b110 #
b110 ,
b110 ;
1)
0*
#380000000000000
0)
#385000000000000
b10000 H
b101 L
b0 9
b110 8
b0 K
b0 J
1)
#390000000000000
0)
#395000000000000
b100000 H
b100 L
b1 J
b101 K
b111 8
1)
#400000000000000
0)
#405000000000000
b101 :
b1000000 H
b11 L
b10000 1
00
b0 8
b1101 K
b10 J
1)
#410000000000000
0)
#415000000000000
b10000 H
b11111 L
b100 :
b100000 1
10
b11 J
b11001 K
b1 8
b101 9
1)
#420000000000000
0)
#425000000000000
b11 :
b100000 H
b1001 L
b1101 9
b10 8
b111000 K
b100 J
1)
#430000000000000
0)
#435000000000000
b0 L
b10 :
b10000 1
00
b101 J
b1001010 K
b11 8
b10011 9
1)
#440000000000000
0)
#445000000000000
b0 :
b100000 1
10
b10101 9
b100 8
07
b110 J
0I
1)
#450000000000000
0)
#455000000000000
b1001010 !
b1001010 <
b1001010 G
b10101 "
b10101 -
b10101 6
1)
#460000000000000
0)
#465000000000000
1)
#470000000000000
0)
#475000000000000
1I
b100 D
b101 C
b110 B
b11111 F
b1001010 E
17
b11 5
b100 4
b101 3
b110 2
1)
1*
#480000000000000
0)
#485000000000000
b101 8
b111 J
1)
0*
#490000000000000
0)
#495000000000000
b10000 H
b110 L
b0 J
b0 K
b110 8
b0 9
1)
#500000000000000
0)
#505000000000000
b100000 H
b101 L
b111 8
b110 K
b1 J
1)
#510000000000000
0)
#515000000000000
b1000000 H
b100 L
b110 :
b10000 1
00
b10 J
b10000 K
b0 8
1)
#520000000000000
0)
#525000000000000
b101 :
b10000 H
b1001010 L
b100000 1
10
b110 9
b1 8
b100000 K
b11 J
1)
#530000000000000
0)
#535000000000000
b100000 H
b11111 L
b100 :
b100 J
b1101010 K
b10 8
b10000 9
1)
#540000000000000
0)
#545000000000000
b11 :
b0 L
b10000 1
00
b11000 9
b11 8
b10101000 K
b101 J
1)
#550000000000000
0)
#555000000000000
b0 :
b100000 1
10
0I
b110 J
07
b100 8
b11011 9
1)
#560000000000000
0)
#565000000000000
b11011 "
b11011 -
b11011 6
b10101000 !
b10101000 <
b10101000 G
1)
